README.md
setup.cfg
setup.py
src/bunnycdn_storage/__init__.py
src/bunnycdn_storage/storage.py
src/python_bunnycdn_storage.egg-info/PKG-INFO
src/python_bunnycdn_storage.egg-info/SOURCES.txt
src/python_bunnycdn_storage.egg-info/dependency_links.txt
src/python_bunnycdn_storage.egg-info/not-zip-safe
src/python_bunnycdn_storage.egg-info/requires.txt
src/python_bunnycdn_storage.egg-info/top_level.txt