Metadata-Version: 2.1
Name: python-bunnycdn-storage
Version: 0.1.1
Summary: This package provides Bunny.net file storage for Django.
Home-page: https://github.com/exceptionalvic/python-bunnycdn-storage
Author: Victor Igbokwe
Author-email: victor@victorigbokwe.site
Maintainer: Victor Igbokwe
Maintainer-email: victor@victorigbokwe.site
License: MIT License
Keywords: django,storage,files
Platform: UNKNOWN
Classifier: Environment :: Web Environment
Classifier: Framework :: Django
Classifier: Framework :: Django :: 3.0
Classifier: Framework :: Django :: 3.1
Classifier: Framework :: Django :: 3.2
Classifier: Framework :: Django :: 4.0
Classifier: Intended Audience :: Developers
Classifier: License :: OSI Approved :: MIT License
Classifier: Operating System :: OS Independent
Classifier: Programming Language :: Python
Classifier: Programming Language :: Python :: 3
Classifier: Programming Language :: Python :: 3.7
Classifier: Programming Language :: Python :: 3.8
Classifier: Programming Language :: Python :: 3.9
Classifier: Programming Language :: Python :: 3.10
Classifier: Topic :: Software Development :: Libraries :: Application Frameworks
Classifier: Topic :: Software Development :: Libraries :: Python Modules
Requires-Python: >=3.7
